graphscope-0.29.0.dist-info/METADATA
graphscope-0.29.0.dist-info/RECORD
graphscope-0.29.0.dist-info/top_level.txt
graphscope-0.29.0.dist-info/WHEEL
graphscope_runtime/__init__.py
graphscope.libs/libglog-991c7a17.so.0.6.0
graphscope.libs/libboost_thread-6e0a2c1f.so.1.75.0
graphscope.libs/libabsl_spinlock_wait-3e59ab9d.so.2206.0.0
graphscope.libs/libabsl_strings-89768255.so.2206.0.0
graphscope.libs/libabsl_synchronization-dbcda29d.so.2206.0.0
graphscope.libs/libvineyard_basic-11afda7f.so
graphscope.libs/libidn-97d26f25.so.11.6.11
graphscope.libs/libgs_util-b712f9f5.so
graphscope.libs/libprotobuf-f210f9d0.so.32.0.9
graphscope.libs/libopen-pal-e578198b.so.40.20.5
graphscope.libs/libabsl_random_internal_platform-8c7a1ac4.so.2206.0.0
graphscope.libs/libabsl_malloc_internal-9ea25431.so.2206.0.0
graphscope.libs/libabsl_str_format_internal-d45e53ed.so.2206.0.0
graphscope.libs/libabsl_cordz_functions-163aeeb8.so.2206.0.0
graphscope.libs/libpcre-9513aab5.so.1.2.0
graphscope.libs/libopen-rte-2a7aebdd.so.40.20.5
graphscope.libs/libabsl_strings_internal-d7a50ef3.so.2206.0.0
graphscope.libs/libldap-2-b8523ca2.4.so.2.10.7
graphscope.libs/libplc4-690d9cce.so
graphscope.libs/libabsl_random_internal_randen_slow-1bf5ddf5.so.2206.0.0
graphscope.libs/libmpi_cxx-d71adff4.so.40.20.1
graphscope.libs/libgomp-a34b3233.so.1.0.0
graphscope.libs/libabsl_random_distributions-7813efe8.so.2206.0.0
graphscope.libs/libgrpc++-7da7acfa.so.1.49.1
graphscope.libs/libabsl_exponential_biased-1f2152b2.so.2206.0.0
graphscope.libs/libsasl2-84219a89.so.3.0.0
graphscope.libs/libabsl_strerror-dba4128a.so.2206.0.0
graphscope.libs/libabsl_time-cf2dc4e6.so.2206.0.0
graphscope.libs/libgpr-38b96f6e.so.27.0.0
graphscope.libs/libcom_err-2abe824b.so.2.1
graphscope.libs/libkrb5support-d0bcff84.so.0.1
graphscope.libs/libabsl_cord-99a096ba.so.2206.0.0
graphscope.libs/libboost_regex-b1d79cea.so.1.75.0
graphscope.libs/libabsl_random_internal_randen-25e43188.so.2206.0.0
graphscope.libs/libabsl_int128-6cee0792.so.2206.0.0
graphscope.libs/libabsl_hash-a56eac96.so.2206.0.0
graphscope.libs/libarrow-6b18b6b8.so.1500.2.0
