Metadata-Version: 2.1
Name: graphscope
Version: 0.29.0
Home-page: https://github.com/alibaba/GraphScope
Author: GraphScope Team, Damo Academy
Author-email: graphscope@alibaba-inc.com
License: Apache License 2.0
Keywords: GraphScope,Graph Computations
Classifier: Development Status :: 5 - Production/Stable
Classifier: Intended Audience :: Developers
Classifier: License :: OSI Approved :: Apache Software License
Classifier: Topic :: Software Development :: Libraries
Classifier: Topic :: System :: Distributed Computing
Classifier: Operating System :: MacOS :: MacOS X
Classifier: Operating System :: POSIX
Classifier: Programming Language :: Python
Classifier: Programming Language :: Python :: 3
Classifier: Programming Language :: Python :: 3.7
Classifier: Programming Language :: Python :: 3.8
Classifier: Programming Language :: Python :: 3.9
Classifier: Programming Language :: Python :: 3.10
Classifier: Programming Language :: Python :: 3.11
Requires-Dist: gs-coordinator==0.29.0
Requires-Dist: gs-engine==0.29.0
Requires-Dist: gs-include==0.29.0
Requires-Dist: gs-apps==0.29.0
